league_ranker/__init__.py
league_ranker/py.typed
league_ranker-1.0.5.dist-info/AUTHORS.rst
league_ranker-1.0.5.dist-info/LICENSE
league_ranker-1.0.5.dist-info/METADATA
league_ranker-1.0.5.dist-info/WHEEL
league_ranker-1.0.5.dist-info/top_level.txt
league_ranker-1.0.5.dist-info/zip-safe
league_ranker-1.0.5.dist-info/RECORD
