Metadata-Version: 2.1
Name: league-ranker
Version: 1.0.5
Summary: League ranking for arbitrary numbers of competitors.
Home-page: https://ranker.readthedocs.io/en/latest/
Author: Student Robotics Competition Software SIG
Author-email: srobo-devel@googlegroups.com
License: MIT
Project-URL: Documentation, https://ranker.readthedocs.io/en/latest/
Project-URL: Code, https://github.com/PeterJCLaw/ranker
Project-URL: Issue tracker, https://github.com/PeterJCLaw/ranker/issues
Platform: UNKNOWN
Classifier: Development Status :: 5 - Production/Stable
Classifier: Intended Audience :: Developers
Classifier: License :: OSI Approved :: MIT License
Classifier: Operating System :: OS Independent
Classifier: Programming Language :: Python
Classifier: Programming Language :: Python :: 3 :: Only
Classifier: Programming Language :: Python :: 3.7
Classifier: Programming Language :: Python :: 3.8
Classifier: Programming Language :: Python :: 3.9
Classifier: Programming Language :: Python :: 3.10
Classifier: Programming Language :: Python :: 3.11
Classifier: Programming Language :: Python :: 3.12
Classifier: Programming Language :: Python :: 3.13
Classifier: Topic :: Software Development :: Libraries :: Python Modules
Classifier: Typing :: Typed
Requires-Python: >=3.7
